grazie/__init__.py
grazie/api/__init__.py
grazie/api/client/__init__.py
grazie/api/client/__main__.py
grazie/api/client/_common.py
grazie/api/client/chat/__init__.py
grazie/api/client/chat/message.py
grazie/api/client/chat/prompt.py
grazie/api/client/chat/response.py
grazie/api/client/chat/roles.py
grazie/api/client/completion/__init__.py
grazie/api/client/completion/prompt.py
grazie/api/client/completion/response.py
grazie/api/client/emb/__init__.py
grazie/api/client/emb/request.py
grazie/api/client/emb/response.py
grazie/api/client/endpoints.py
grazie/api/client/gateway.py
grazie/api/client/llm_functions.py
grazie/api/client/llm_parameters.py
grazie/api/client/parameters.py
grazie/api/client/profiles.py
grazie/api/client/qna/__init__.py
grazie/api/client/qna/request.py
grazie/api/client/qna/response.py
grazie/api/client/quota/__init__.py
grazie/api/client/quota/response.py
grazie/api/client/utils.py
grazie/api/client/v8/chat/message.py
grazie/api/client/v8/chat/prompt.py
grazie/api/client/v8/chat/response.py
grazie/api/client/v8/chat/roles.py
grazie/api/client/v8/completion/prompt.py
grazie/api/client/v8/completion/response.py
grazie/api/client/v8/llm_parameters.py
grazie/api/client/v8/llm_tools.py
grazie/api/client/v8/parameters.py
grazie/api/client_v2/__init__.py
grazie/api/client_v2/_api.py
grazie/api/client_v2/_client.py
grazie/api/client_v2/_gateway_client.py
grazie/api/client_v2/_sse.py
grazie/api/client_v2/_version.py
grazie/api/client_v2/exceptions.py
grazie/api/client_v2/tasks/__init__.py
grazie/api/client_v2/tasks/api.py
grazie/api/client_v2/tasks/types.py
grazie/api/client_v2/types.py
grazie/py.typed
grazie_api_gateway_client-0.3.3.dist-info/METADATA
grazie_api_gateway_client-0.3.3.dist-info/WHEEL
grazie_api_gateway_client-0.3.3.dist-info/RECORD
