Metadata-Version: 2.3
Name: grazie_api_gateway_client
Version: 0.3.3
Summary: Api client for Grazie services
License: Apache-2.0
Author: JetBrains
Requires-Python: >=3.8
Classifier: License :: OSI Approved :: Apache Software License
Classifier: Programming Language :: Python :: 3
Classifier: Programming Language :: Python :: 3.8
Classifier: Programming Language :: Python :: 3.9
Classifier: Programming Language :: Python :: 3.10
Classifier: Programming Language :: Python :: 3.11
Classifier: Programming Language :: Python :: 3.12
Classifier: Programming Language :: Python :: 3.13
Requires-Dist: attrs (>=23.1.0)
Requires-Dist: cbor2 (>=5.4.6,<6.0.0)
Requires-Dist: httpx (>=0.23.0,<1)
Requires-Dist: jsonschema (>=4.17.3,<5.0.0)
Requires-Dist: pydantic (>1.9,<3)
Requires-Dist: requests (>=2.26.0,<3.0.0)
